metadsl_rewrite/__init__.py
metadsl_rewrite/combinators.py
metadsl_rewrite/normalize.py
metadsl_rewrite/rules.py
metadsl_rewrite/rules_test.py
metadsl_rewrite/strategies.py
metadsl_rewrite-0.1.0.dist-info/WHEEL
metadsl_rewrite-0.1.0.dist-info/METADATA
metadsl_rewrite-0.1.0.dist-info/RECORD
